AUTHORS.rst
CONTRIBUTING.rst
HISTORY.rst
LICENSE
MANIFEST.in
README.rst
setup.cfg
setup.py
ceedub/__init__.py
ceedub/wavelet.py
ceedub.egg-info/PKG-INFO
ceedub.egg-info/SOURCES.txt
ceedub.egg-info/dependency_links.txt
ceedub.egg-info/not-zip-safe
ceedub.egg-info/requires.txt
ceedub.egg-info/top_level.txt
docs/Makefile
docs/authors.rst
docs/ceedub.rst
docs/conf.py
docs/contributing.rst
docs/history.rst
docs/index.rst
docs/installation.rst
docs/make.bat
docs/modules.rst
docs/readme.rst
docs/usage.rst
docs/_build/html/_static/ajax-loader.gif
docs/_build/html/_static/comment-bright.png
docs/_build/html/_static/comment-close.png
docs/_build/html/_static/comment.png
docs/_build/html/_static/down-pressed.png
docs/_build/html/_static/down.png
docs/_build/html/_static/file.png
docs/_build/html/_static/minus.png
docs/_build/html/_static/plus.png
docs/_build/html/_static/up-pressed.png
docs/_build/html/_static/up.png
tests/__init__.py
tests/test_wavelet.py