Metadata-Version: 1.1
Name: ceedub
Version: 0.1.0
Summary: (CW) an awesome and simple continuous wavelet transform
Home-page: https://github.com/paulthebaker/ceedub
Author: Paul T. Baker
Author-email: paultbaker@gmail.com
License: MIT license
Download-URL: https://github.com/paulthebaker/ceedub/archive/
Keywords: cwt,wavelet
Platform: UNKNOWN
Classifier: Development Status :: 3 - Alpha
Classifier: Intended Audience :: Developers
Classifier: Intended Audience :: Education
Classifier: Intended Audience :: Science/Research
Classifier: License :: OSI Approved :: MIT License
Classifier: Natural Language :: English
Classifier: Programming Language :: Python :: 2
Classifier: Programming Language :: Python :: 2.7
Classifier: Programming Language :: Python :: 3
Classifier: Programming Language :: Python :: 3.5
Classifier: Programming Language :: Python :: 3.6
Classifier: Topic :: Scientific/Engineering
